{
    "type": "Collection",
    "id": "USGS/GFSAD1000_V0",
    "stac_version": "1.0.0",
    "description": "The GFSAD is a NASA-funded project to provide high-resolution global\ncropland data and their water use that contributes towards global food\nsecurity in the twenty-first century. The GFSAD products are derived\nthrough multi-sensor remote sensing data (e.g., Landsat, MODIS, AVHRR),\nsecondary data, and field-plot data and aims at documenting cropland\ndynamics.\n\nAt a nominal 1km scale, V0.0 provides the spatial distribution of the\nfive major global cropland types (wheat, rice, corn, barley, and soybeans)\nwhich occupy 60% of all global cropland areas. The map is produced by\noverlaying these crops over the remote sensing derived global irrigated and\nrainfed cropland area map of the International Water Management Institute.\nV0.0 an 8-class product that provides information on global: cropland\nextent, crop dominance, irrigated versus rainfed cropping, and cropping\nintensity (single, double, triple, and continuous crops). The GFSAD1000\nnominal 2010 product was created with data from 2007 to 2012.\n",
    "links": [
        {
            "rel": "root",
            "href": "https://storage.googleapis.com/earthengine-stac/catalog/catalog.json",
            "type": "application/json",
            "title": "Google Earth Engine Catalog"
        },
        {
            "rel": "related",
            "href": "https://code.earthengine.google.com/?scriptPath=Examples:Datasets/USGS/USGS_GFSAD1000_V0",
            "type": "text/html",
            "title": "Run the example for USGS/GFSAD1000_V0 in the Earth Engine Code Editor",
            "code": "JavaScript"
        },
        {
            "rel": "preview",
            "href": "https://developers.google.com/earth-engine/datasets/images/USGS/USGS_GFSAD1000_V0_sample.png",
            "type": "image/png"
        },
        {
            "rel": "license",
            "href": "https://developers.google.com/earth-engine/datasets/catalog/USGS_GFSAD1000_V0#terms-of-use",
            "type": "text/html"
        },
        {
            "rel": "successor-version",
            "href": "https://storage.googleapis.com/earthengine-stac/catalog/USGS/USGS_GFSAD1000_V1.json",
            "type": "application/json",
            "title": "USGS/GFSAD1000_V1"
        },
        {
            "rel": "self",
            "href": "https://storage.googleapis.com/earthengine-stac/catalog/USGS/USGS_GFSAD1000_V0.json",
            "type": "application/json"
        },
        {
            "rel": "parent",
            "href": "https://storage.googleapis.com/earthengine-stac/catalog/USGS/catalog.json",
            "type": "application/json",
            "title": "USGS"
        }
    ],
    "stac_extensions": [
        "https://stac-extensions.github.io/eo/v1.0.0/schema.json",
        "https://stac-extensions.github.io/scientific/v1.0.0/schema.json",
        "https://stac-extensions.github.io/version/v1.0.0/schema.json"
    ],
    "deprecated": true,
    "gee:terms_of_use": "Most U.S. Geological Survey (USGS) information resides\nin the public domain and may be used without restriction. Additional\ninformation on [Acknowledging or Crediting USGS as Information\nSource](https://www.usgs.gov/information-policies-and-instructions/crediting-usgs) is available.\n",
    "gee:type": "image",
    "sci:citation": "Thenkabail P.S., Knox J.W., Ozdogan, M., Gumma, M.K., Congalton, R.G., Wu,\nZ., Milesi, C., Finkral, A., Marshall, M., Mariotto, I., You, S. Giri, C.\nand Nagler, P. 2012. Assessing future risks to agricultural productivity,\nwater resources and food security: how can remote sensing help?.\nPhotogrammetric Engineering and Remote Sensing, August 2012 Special Issue\non Global Croplands: Highlight Article. 78(8): 773-782.\n",
    "version": "V0.0",
    "title": "GFSAD1000: Cropland Extent 1km Crop Dominance, Global Food-Support Analysis Data [deprecated]",
    "extent": {
        "spatial": {
            "bbox": [
                [
                    -180,
                    -90,
                    180,
                    90
                ]
            ]
        },
        "temporal": {
            "interval": [
                [
                    "2010-01-01T00:00:00Z",
                    "2011-01-01T00:00:00Z"
                ]
            ]
        }
    },
    "license": "proprietary",
    "keywords": [
        "crop",
        "cropland",
        "gfsad",
        "landcover",
        "usgs"
    ],
    "providers": [
        {
            "name": "Global Food Security-support Analysis Data at 30m Project (GFSAD30)",
            "roles": [
                "licensor",
                "producer"
            ],
            "url": "https://geography.wr.usgs.gov/science/croplands/"
        },
        {
            "name": "Google Earth Engine",
            "roles": [
                "host"
            ],
            "url": "https://developers.google.com/earth-engine/datasets/catalog/USGS_GFSAD1000_V0"
        }
    ],
    "summaries": {
        "eo:bands": [
            {
                "description": "Crop dominance class descriptions",
                "gee:classes": [
                    {
                        "color": "black",
                        "description": "Non-croplands",
                        "value": 0
                    },
                    {
                        "color": "white",
                        "description": "Irrigated: wheat and rice",
                        "value": 1
                    },
                    {
                        "color": "green",
                        "description": "Irrigated mixed crops 1: Wheat, rice, barley, soybeans",
                        "value": 2
                    },
                    {
                        "color": "yellow",
                        "description": "Irrigated mixed crops 2: wheat, rice, cotton, orchards",
                        "value": 3
                    },
                    {
                        "color": "brown",
                        "description": "Rainfed: wheat, rice, soybeans, sugarcane, corn, cassava",
                        "value": 4
                    },
                    {
                        "color": "orange",
                        "description": "Rainfed: wheat, barley",
                        "value": 5
                    },
                    {
                        "color": "forestgreen",
                        "description": "Rainfed: corn, soybens",
                        "value": 6
                    },
                    {
                        "color": "darkgreen",
                        "description": "Rainfed mixed crops: wheat, corn, rice, barley, soybeans",
                        "value": 7
                    },
                    {
                        "color": "darkseagreen",
                        "description": "Fractions of mixed crops: wheat, maize, rice, barley, soybeans",
                        "value": 8
                    },
                    {
                        "color": "purple",
                        "description": "Other classes",
                        "value": 9
                    }
                ],
                "name": "landcover"
            }
        ],
        "gee:visualizations": [
            {
                "display_name": "Crop Dominance",
                "image_visualization": {
                    "band_vis": {
                        "bands": [
                            "landcover"
                        ],
                        "max": [
                            9
                        ],
                        "min": [
                            0
                        ],
                        "palette": [
                            "black",
                            "white",
                            "green",
                            "yellow",
                            "brown",
                            "orange",
                            "forestgreen",
                            "darkgreen",
                            "darkseagreen",
                            "purple"
                        ]
                    }
                },
                "lookat": {
                    "lat": 26.4,
                    "lon": -88.6,
                    "zoom": 1
                }
            }
        ],
        "gsd": [
            1000
        ],
        "landcover": {
            "minimum": 0,
            "maximum": 9
        }
    }
}